ncsn/__init__.py
ncsn/pipeline_ncsn.py
ncsn/scheduler/__init__.py
ncsn/scheduler/scheduling_ncsn.py
ncsn/unet/__init__.py
ncsn/unet/unet_2d_ncsn.py
diffusers_ncsn-0.1.0.dist-info/METADATA
diffusers_ncsn-0.1.0.dist-info/WHEEL
diffusers_ncsn-0.1.0.dist-info/licenses/LICENSE
diffusers_ncsn-0.1.0.dist-info/RECORD
