Metadata-Version: 2.4
Name: diffusers-ncsn
Version: 0.1.0
Summary: Diffusers implementation of Noise Conditional Score Networks (NCSN) [Yang+ NeuriPS'19]
Author-email: Shunsuke Kitada <shunsuke.kitada.0831@gmail.com>, Image Generation with Python <python.image.generation@gmail.com>
License-Expression: Apache-2.0
License-File: LICENSE
Keywords: diffusers,generative-model,ncsn,noise conditional score networks,python
Classifier: Intended Audience :: Developers
Classifier: Programming Language :: Python :: 3
Classifier: Programming Language :: Python :: 3.10
Classifier: Programming Language :: Python :: 3.11
Requires-Python: >=3.10
Requires-Dist: diffusers[torch]>=0.31.0
Requires-Dist: einops>=0.7.0
Requires-Dist: torch>=1.0.0
Requires-Dist: torchvision>=0.2.1
Requires-Dist: transformers>=4.30.0
Provides-Extra: doc
Requires-Dist: furo>=2024.8.6; extra == 'doc'
Requires-Dist: myst-parser>=4.0.0; extra == 'doc'
Requires-Dist: sphinx-autodoc-typehints>=3.0.0; extra == 'doc'
Requires-Dist: sphinx-pyproject>=0.3.0; extra == 'doc'
Requires-Dist: sphinx>=8.1.3; extra == 'doc'
Provides-Extra: training
Requires-Dist: matplotlib>=3.10.0; extra == 'training'
